nonebot_plugin_orangedice/__init__.py
nonebot_plugin_orangedice/config.py
nonebot_plugin_orangedice/dice.py
nonebot_plugin_orangedice/message.py
nonebot_plugin_orangedice/model.py
nonebot_plugin_orangedice/roll.py
nonebot_plugin_orangedice/utils.py
nonebot_plugin_orangedice-0.3.9.dist-info/WHEEL
nonebot_plugin_orangedice-0.3.9.dist-info/METADATA
nonebot_plugin_orangedice-0.3.9.dist-info/licenses/LICENSE
nonebot_plugin_orangedice-0.3.9.dist-info/RECORD
