Metadata-Version: 2.1
Name: nonebot_plugin_orangedice
Version: 0.3.9
Summary: A COC dice plugin for nonebot2
License: MIT
Author-email: BigOrangeQWQ <2284086963@qq.com>
Requires-Python: >=3.8
Requires-Dist: nonebot-adapter-onebot>=2.2.3
Requires-Dist: nonebot2>=2.0.1
Requires-Dist: pydantic>=1.9.2
Requires-Dist: sqlmodel>=0.0.8
